ParallelBayesOpt-0.9.2.dist-info/DESCRIPTION.rst
ParallelBayesOpt-0.9.2.dist-info/METADATA
ParallelBayesOpt-0.9.2.dist-info/RECORD
ParallelBayesOpt-0.9.2.dist-info/WHEEL
ParallelBayesOpt-0.9.2.dist-info/metadata.json
ParallelBayesOpt-0.9.2.dist-info/top_level.txt
optimizer/__init__.py
optimizer/cma_es.py
optimizer/mies.py
