Metadata-Version: 2.0
Name: ParallelBayesOpt
Version: 0.9.2
Summary: Bayesian Optimization Library with GPU support
Home-page: https://github.com/wangronin/BayesianOptimization
Author: Hao Wang and Bas van Stein
Author-email: wangronin@gmail.com
License: UNKNOWN
Keywords: bayesian optimization neuralnetworks
Platform: UNKNOWN
Classifier: Development Status :: 4 - Beta
Classifier: Intended Audience :: Science/Research
Classifier: Topic :: Scientific/Engineering :: Artificial Intelligence
Classifier: License :: OSI Approved :: MIT License
Classifier: Programming Language :: Python :: 2
Classifier: Programming Language :: Python :: 2.7
Classifier: Programming Language :: Python :: 3
Classifier: Programming Language :: Python :: 3.4
Classifier: Programming Language :: Python :: 3.5
Classifier: Programming Language :: Python :: 3.6
Requires-Dist: pandas
Requires-Dist: numpy
Requires-Dist: scipy
Requires-Dist: scikit-learn
